aineko_plugins/nodes/fastapi_server/__init__.py
aineko_plugins/nodes/fastapi_server/health.py
aineko_plugins/nodes/fastapi_server/main.py
aineko_plugins/nodes/fastapi_server/py.typed
aineko_plugins_nodes_fastapi_server-0.0.3.dist-info/LICENSE
aineko_plugins_nodes_fastapi_server-0.0.3.dist-info/METADATA
aineko_plugins_nodes_fastapi_server-0.0.3.dist-info/WHEEL
aineko_plugins_nodes_fastapi_server-0.0.3.dist-info/RECORD
